LICENSE
README.md
setup.py
cryptiles/__init__.py
cryptiles/__main__.py
cryptiles/cryptile.py
cryptiles/cryptile_parse.py
cryptiles.egg-info/PKG-INFO
cryptiles.egg-info/SOURCES.txt
cryptiles.egg-info/dependency_links.txt
cryptiles.egg-info/entry_points.txt
cryptiles.egg-info/not-zip-safe
cryptiles.egg-info/requires.txt
cryptiles.egg-info/top_level.txt