Metadata-Version: 1.0
Name: cryptiles
Version: 0.1
Summary: A simple script to encrypt and decrypt data.
Home-page: http://github.com/kanazux/cryptiles
Author: Silvio Ap Silva a.k.a Kanazuchi
Author-email: contato@kanazuchi.com
License: BSD2CLAUSE
Platform: UNKNOWN
